worstpractices/__init__.py
worstpractices/cmd.py
worstpractices/packaging.py
worstpractices/rl/__init__.py
worstpractices/rl/rainbow.py
worstpractices/rl/util.py
worstpractices/serialize.py
worstpractices/typing.py
worstpractices/util.py
worstpractices-0.1.1.dist-info/entry_points.txt
worstpractices-0.1.1.dist-info/LICENSE
worstpractices-0.1.1.dist-info/WHEEL
worstpractices-0.1.1.dist-info/METADATA
worstpractices-0.1.1.dist-info/RECORD
