Metadata-Version: 2.1
Name: worstpractices
Version: 0.1.1
Summary: An opinionanted library of Python/ML practices
License: MIT
Author: Vadim Liventsev
Author-email: dev@vadim.me
Requires-Python: >=3.9,<4.0
Classifier: License :: OSI Approved :: MIT License
Classifier: Programming Language :: Python :: 3
Classifier: Programming Language :: Python :: 3.9
Classifier: Programming Language :: Python :: 3.10
Provides-Extra: rl
Requires-Dist: fire (<1.0.0)
